[
  {
    "full_name": "thuss/standalone-migrations",
    "stargazers_count": 943,
    "open_issues_count": 15,
    "forks_count": 135
  },
  {
    "full_name": "jeremyevans/sequel",
    "stargazers_count": 4480,
    "open_issues_count": 0,
    "forks_count": 1014
  },
  {
    "full_name": "opal/opal",
    "stargazers_count": 4518,
    "open_issues_count": 133,
    "forks_count": 327
  },
  {
    "full_name": "fnando/i18n-js",
    "stargazers_count": 3457,
    "open_issues_count": 9,
    "forks_count": 513
  },
  {
    "full_name": "bootstrap-vue/bootstrap-vue",
    "stargazers_count": 13399,
    "open_issues_count": 166,
    "forks_count": 1795
  },
  {
    "full_name": "hoppscotch/hoppscotch",
    "stargazers_count": 30839,
    "open_issues_count": 32,
    "forks_count": 2147
  },
  {
    "full_name": "tonsky/FiraCode",
    "stargazers_count": 57958,
    "open_issues_count": 282,
    "forks_count": 2620
  },
  {
    "full_name": "cs01/gdbgui",
    "stargazers_count": 8140,
    "open_issues_count": 111,
    "forks_count": 482
  },
  {
    "full_name": "directus/directus",
    "stargazers_count": 11978,
    "open_issues_count": 104,
    "forks_count": 1262
  },
  {
    "full_name": "strapi/strapi",
    "stargazers_count": 39220,
    "open_issues_count": 597,
    "forks_count": 4725
  },
  {
    "full_name": "vuejs/vue",
    "stargazers_count": 187551,
    "open_issues_count": 527,
    "forks_count": 30030
  },
  {
    "full_name": "kuchin/awesome-cto",
    "stargazers_count": 10366,
    "open_issues_count": 0,
    "forks_count": 567
  },
  {
    "full_name": "webview/webview",
    "stargazers_count": 8800,
    "open_issues_count": 251,
    "forks_count": 682
  },
  {
    "full_name": "ffi/ffi",
    "stargazers_count": 1880,
    "open_issues_count": 105,
    "forks_count": 301
  },
  {
    "full_name": "piotrmurach/tty-box",
    "stargazers_count": 167,
    "open_issues_count": 1,
    "forks_count": 16
  },
  {
    "full_name": "abdalrahman-ali/vim-remembers",
    "stargazers_count": 20,
    "open_issues_count": 1,
    "forks_count": 0
  },
  {
    "full_name": "danistefanovic/build-your-own-x",
    "stargazers_count": 116201,
    "open_issues_count": 187,
    "forks_count": 10390
  },
  {
    "full_name": "typicode/json-server",
    "stargazers_count": 56058,
    "open_issues_count": 584,
    "forks_count": 5415
  },
  {
    "full_name": "aravindnc/A-to-Z-List-of-Useful-Node.js-Modules",
    "stargazers_count": 326,
    "open_issues_count": 0,
    "forks_count": 95
  },
  {
    "full_name": "tj/commander.js",
    "stargazers_count": 21062,
    "open_issues_count": 9,
    "forks_count": 1494
  },
  {
    "full_name": "twitter/twemoji",
    "stargazers_count": 13180,
    "open_issues_count": 50,
    "forks_count": 1512
  },
  {
    "full_name": "markop159/KODI-Popcorn-Time",
    "stargazers_count": 138,
    "open_issues_count": 38,
    "forks_count": 31
  },
  {
    "full_name": "hishamhm/htop",
    "stargazers_count": 5575,
    "open_issues_count": 321,
    "forks_count": 614
  },
  {
    "full_name": "cmatsuoka/figlet",
    "stargazers_count": 811,
    "open_issues_count": 11,
    "forks_count": 90
  },
  {
    "full_name": "clojure/core.logic",
    "stargazers_count": 1306,
    "open_issues_count": 1,
    "forks_count": 112
  },
  {
    "full_name": "wesbos/es6.io",
    "stargazers_count": 2020,
    "open_issues_count": 16,
    "forks_count": 1148
  },
  {
    "full_name": "oclint/oclint",
    "stargazers_count": 3354,
    "open_issues_count": 17,
    "forks_count": 428
  },
  {
    "full_name": "danmar/cppcheck",
    "stargazers_count": 3654,
    "open_issues_count": 24,
    "forks_count": 1095
  },
  {
    "full_name": "uncrustify/uncrustify",
    "stargazers_count": 2369,
    "open_issues_count": 248,
    "forks_count": 485
  },
  {
    "full_name": "photonstorm/phaser",
    "stargazers_count": 30286,
    "open_issues_count": 196,
    "forks_count": 6526
  }
]